{
    "weaponInfo": [
        {
            "weaponID": 1,
            "currentlevel": 1,
            "firerate": 0.3499999940395355,
            "cost": 10,
            "damage": 2,
            "attackRange": 10.0,
            "attackSpeed": 8.0,
            "pierce": 10,
            "pierceDamageReduce": 10.0
        },
        {
            "weaponID": 1,
            "currentlevel": 2,
            "firerate": 0.30000001192092898,
            "cost": 15,
            "damage": 3,
            "attackRange": 11.0,
            "attackSpeed": 8.5,
            "pierce": 10,
            "pierceDamageReduce": 10.0
        },
        {
            "weaponID": 1,
            "currentlevel": 3,
            "firerate": 0.25,
            "cost": 20,
            "damage": 4,
            "attackRange": 12.0,
            "attackSpeed": 9.0,
            "pierce": 10,
            "pierceDamageReduce": 10.0
        },
        {
            "weaponID": 1,
            "currentlevel": 4,
            "firerate": 0.20000000298023225,
            "cost": 25,
            "damage": 5,
            "attackRange": 13.0,
            "attackSpeed": 9.5,
            "pierce": 10,
            "pierceDamageReduce": 10.0
        },
        {
            "weaponID": 1,
            "currentlevel": 5,
            "firerate": 0.15000000596046449,
            "cost": 25,
            "damage": 6,
            "attackRange": 14.0,
            "attackSpeed": 10.0,
            "pierce": 10,
            "pierceDamageReduce": 10.0
        }
    ]
}